odoo/addons/agreement_sale/README.rst
odoo/addons/agreement_sale/__init__.py
odoo/addons/agreement_sale/__manifest__.py
odoo/addons/agreement_sale/i18n/agreement_sale.pot
odoo/addons/agreement_sale/i18n/de.po
odoo/addons/agreement_sale/models/__init__.py
odoo/addons/agreement_sale/models/agreement.py
odoo/addons/agreement_sale/models/product.py
odoo/addons/agreement_sale/models/sale_order.py
odoo/addons/agreement_sale/readme/CONFIGURE.rst
odoo/addons/agreement_sale/readme/CONTRIBUTORS.rst
odoo/addons/agreement_sale/readme/CREDITS.rst
odoo/addons/agreement_sale/readme/DESCRIPTION.rst
odoo/addons/agreement_sale/readme/ROADMAP.rst
odoo/addons/agreement_sale/readme/USAGE.rst
odoo/addons/agreement_sale/static/description/icon.png
odoo/addons/agreement_sale/static/description/index.html
odoo/addons/agreement_sale/views/agreement.xml
odoo/addons/agreement_sale/views/product.xml
odoo/addons/agreement_sale/views/sale_order.xml
odoo11_addon_agreement_sale-11.0.0.0.1.99.dev12.dist-info/METADATA
odoo11_addon_agreement_sale-11.0.0.0.1.99.dev12.dist-info/WHEEL
odoo11_addon_agreement_sale-11.0.0.0.1.99.dev12.dist-info/top_level.txt
odoo11_addon_agreement_sale-11.0.0.0.1.99.dev12.dist-info/RECORD
